easy_publish/__init__.py
easy_publish/posts.py
easy_publish/utils.py
tests/__init__.py
tests/test_posts.py
tests/test_utils.py
easy_publish-0.0.12.dist-info/LICENSE
easy_publish-0.0.12.dist-info/METADATA
easy_publish-0.0.12.dist-info/WHEEL
easy_publish-0.0.12.dist-info/entry_points.txt
easy_publish-0.0.12.dist-info/top_level.txt
easy_publish-0.0.12.dist-info/RECORD
