Metadata-Version: 2.1
Name: easy-publish
Version: 0.0.12
Summary: A simple abstraction for publishing files as blog posts.
Home-page: https://github.com/samdixon/easy-publish
Author: Samuel Dixon
Author-email: sdixon@posteo.net
License: MIT
Platform: UNKNOWN
Classifier: License :: OSI Approved :: MIT License
Classifier: Programming Language :: Python
Classifier: Programming Language :: Python :: 3
Classifier: Programming Language :: Python :: 3.6
Classifier: Programming Language :: Python :: Implementation :: CPython
Classifier: Programming Language :: Python :: Implementation :: PyPy
Requires-Python: >=3.6.0
Provides-Extra: dev
Requires-Dist: pytest ; extra == 'dev'
Requires-Dist: pytest-cov ; extra == 'dev'
Requires-Dist: jedi ; extra == 'dev'
Requires-Dist: black ; extra == 'dev'
